setup.py
digg6/__init__.py
digg6/gate.py
digg6/generate.py
digg6/minimize.py
digg6/sequential.py
digg6.egg-info/PKG-INFO
digg6.egg-info/SOURCES.txt
digg6.egg-info/dependency_links.txt
digg6.egg-info/top_level.txt