Metadata-Version: 1.1
Name: digg6
Version: 0.1.4
Summary: Digital simulation library!
Home-page: https://khanstark.github.io/DigiSim/
Author: Kaif Khan,Pulak Sahoo,Tushar,Gaurav Singh
Author-email: kaifkhan.khan0@gmail.com
License: MIT
Keywords: digital,electronics,logic gates,flip flops
Platform: UNKNOWN
Classifier: Development Status :: 4 - Beta
Classifier: Intended Audience :: Developers
Classifier: Topic :: Software Development :: Build Tools
Classifier: License :: OSI Approved :: MIT License
Classifier: Programming Language :: Python :: 2
